MANIFEST.in
README.rst
setup.py
docs/HISTORY.rst
docs/INSTALL.txt
docs/LICENSE.GPL
docs/LICENSE.txt
src/Products/__init__.py
src/Products.AutoRoleFromHostHeader.egg-info/PKG-INFO
src/Products.AutoRoleFromHostHeader.egg-info/SOURCES.txt
src/Products.AutoRoleFromHostHeader.egg-info/dependency_links.txt
src/Products.AutoRoleFromHostHeader.egg-info/entry_points.txt
src/Products.AutoRoleFromHostHeader.egg-info/namespace_packages.txt
src/Products.AutoRoleFromHostHeader.egg-info/not-zip-safe
src/Products.AutoRoleFromHostHeader.egg-info/requires.txt
src/Products.AutoRoleFromHostHeader.egg-info/top_level.txt
src/Products/AutoRoleFromHostHeader/__init__.py
src/Products/AutoRoleFromHostHeader/configure.zcml
src/Products/AutoRoleFromHostHeader/interfaces.py
src/Products/AutoRoleFromHostHeader/setuphandlers.py
src/Products/AutoRoleFromHostHeader/plugins/AutoRole.py
src/Products/AutoRoleFromHostHeader/plugins/__init__.py
src/Products/AutoRoleFromHostHeader/plugins/www/autoRoleAdd.zpt
src/Products/AutoRoleFromHostHeader/plugins/www/login_sm.gif
src/Products/AutoRoleFromHostHeader/profiles/default/autorole.txt
src/Products/AutoRoleFromHostHeader/profiles/default/metadata.xml
src/Products/AutoRoleFromHostHeader/tests/__init__.py
src/Products/AutoRoleFromHostHeader/tests/testAutoRole.py
src/Products/AutoRoleFromHostHeader/tests/testCompiler.py
src/Products/AutoRoleFromHostHeader/tests/testEvent.py