Metadata-Version: 1.0
Name: Products.AutoRoleFromHostHeader
Version: 0.4.1
Summary: Plone PAS plugin for adding roles (or groups) to anonymous or logged-in visitors looking for HTTP Headers.
Home-page: http://plone.org/products/autorolefromhostheader
Author: RedTurtle Technology
Author-email: sviluppoplone@redturtle.it
License: GPL
Keywords: autorole pas plugin roles groups http header
Platform: UNKNOWN
Classifier: Framework :: Plone
Classifier: Framework :: Plone :: 3.3
Classifier: Framework :: Plone :: 4.0
Classifier: Framework :: Plone :: 4.1
Classifier: Framework :: Plone :: 4.2
Classifier: Framework :: Plone :: 4.3
Classifier: Framework :: Zope2
Classifier: Programming Language :: Python
Classifier: Development Status :: 5 - Production/Stable
Classifier: Topic :: System :: Systems Administration :: Authentication/Directory
Classifier: Topic :: Software Development :: Libraries :: Python Modules
